.coveragerc
.git-blame-ignore-revs
.mailmap
.pre-commit-config.yaml
.stestr.conf
.zuul.yaml
AUTHORS
CLAUDE.md
CONTRIBUTING.rst
ChangeLog
Dockerfile
EXAMPLES.md
HACKING.rst
INSTALL.md
LICENSE
PUBLISHING.md
README.rst
SETUP_SUMMARY.md
bindep.txt
pyproject.toml
requirements.txt
setup.cfg
setup.py
test-requirements.txt
tox.ini
doc/Makefile
doc/requirements.txt
doc/source/conf.py
doc/source/index.rst
doc/source/_extra/.htaccess
doc/source/cli/authentication.rst
doc/source/cli/backwards-incompatible.rst
doc/source/cli/command-list.rst
doc/source/cli/commands.rst
doc/source/cli/decoder.rst
doc/source/cli/index.rst
doc/source/cli/interactive.rst
doc/source/cli/_hidden/ec2-credentials.rst
doc/source/cli/_hidden/endpoint.rst
doc/source/cli/_hidden/image.rst
doc/source/cli/_hidden/project.rst
doc/source/cli/_hidden/role.rst
doc/source/cli/_hidden/service.rst
doc/source/cli/_hidden/token.rst
doc/source/cli/_hidden/user.rst
doc/source/cli/command-objects/access-rules.rst
doc/source/cli/command-objects/access-token.rst
doc/source/cli/command-objects/address-group.rst
doc/source/cli/command-objects/address-scope.rst
doc/source/cli/command-objects/aggregate.rst
doc/source/cli/command-objects/application-credentials.rst
doc/source/cli/command-objects/availability-zone.rst
doc/source/cli/command-objects/block-storage-cleanup.rst
doc/source/cli/command-objects/block-storage-cluster.rst
doc/source/cli/command-objects/block-storage-log-level.rst
doc/source/cli/command-objects/block-storage-manage.rst
doc/source/cli/command-objects/block-storage-resource-filter.rst
doc/source/cli/command-objects/catalog.rst
doc/source/cli/command-objects/command.rst
doc/source/cli/command-objects/complete.rst
doc/source/cli/command-objects/compute-agent.rst
doc/source/cli/command-objects/compute-service.rst
doc/source/cli/command-objects/configuration.rst
doc/source/cli/command-objects/consistency-group-snapshot.rst
doc/source/cli/command-objects/consistency-group.rst
python_cvmclient.egg-info/PKG-INFO
python_cvmclient.egg-info/SOURCES.txt
python_cvmclient.egg-info/dependency_links.txt
python_cvmclient.egg-info/entry_points.txt
python_cvmclient.egg-info/not-zip-safe
python_cvmclient.egg-info/pbr.json
python_cvmclient.egg-info/requires.txt
python_cvmclient.egg-info/top_level.txt
