Metadata-Version: 2.4
Name: python-cvmclient
Version: 0.1.0
Summary: ConnectVM Command-line Client
Home-page: https://console.connectvm.com/
Author: ConnectVM
Author-email: ConnectVM <support@connectvm.com>
License: Apache-2.0
Project-URL: Homepage, https://console.connectvm.com/
Project-URL: Repository, https://github.com/connectvm/connectvm-cli/
Classifier: Environment :: OpenStack
Classifier: Intended Audience :: Information Technology
Classifier: Intended Audience :: System Administrators
Classifier: License :: OSI Approved :: Apache Software License
Classifier: Operating System :: POSIX :: Linux
Classifier: Programming Language :: Python
Classifier: Programming Language :: Python :: 3
Classifier: Programming Language :: Python :: 3.10
Classifier: Programming Language :: Python :: 3.11
Classifier: Programming Language :: Python :: 3.12
Classifier: Programming Language :: Python :: 3.13
Requires-Python: >=3.10
License-File: LICENSE
Requires-Dist: pbr!=2.1.0,>=2.0.0
Requires-Dist: cryptography>=2.7
Requires-Dist: cliff>=4.8.0
Requires-Dist: iso8601>=0.1.11
Requires-Dist: openstacksdk>=4.6.0
Requires-Dist: osc-lib>=2.3.0
Requires-Dist: oslo.i18n>=3.15.3
Requires-Dist: python-keystoneclient>=3.22.0
Requires-Dist: python-cinderclient>=3.3.0
Requires-Dist: requests>=2.27.0
Requires-Dist: stevedore>=2.0.1
Dynamic: author
Dynamic: home-page
Dynamic: license-file
Dynamic: requires-dist
Dynamic: requires-python
